Pokemona/__init__.py
Pokemona/pokemon.csv
Pokemona/random_pokemon.py
Pokemona-1.0.1.dist-info/METADATA
Pokemona-1.0.1.dist-info/WHEEL
Pokemona-1.0.1.dist-info/top_level.txt
Pokemona-1.0.1.dist-info/RECORD
