Metadata-Version: 2.1
Name: Pokemona
Version: 1.0.1
Summary: Libreria para generar un Pokemon aleatorio
Author: Alexis Gonzales
Author-email: axelgoma11@gmail.com
Requires-Dist: pandas
